jupyterlab_gallery/__init__.py
jupyterlab_gallery/_version.py
jupyterlab_gallery/app.py
jupyterlab_gallery/git_askpass.py
jupyterlab_gallery/git_utils.py
jupyterlab_gallery/gitpuller.py
jupyterlab_gallery/handlers.py
jupyterlab_gallery/hub.py
jupyterlab_gallery/manager.py
jupyterlab_gallery/tests/__init__.py
jupyterlab_gallery/tests/test_handlers.py
jupyterlab_gallery-0.6.3.data/data/etc/jupyter/jupyter_server_config.d/jupyterlab_gallery.json
jupyterlab_gallery-0.6.3.data/data/share/jupyter/labextensions/jupyterlab-gallery/package.json
jupyterlab_gallery-0.6.3.data/data/share/jupyter/labextensions/jupyterlab-gallery/schemas/jupyterlab-gallery/package.json.orig
jupyterlab_gallery-0.6.3.data/data/share/jupyter/labextensions/jupyterlab-gallery/schemas/jupyterlab-gallery/plugin.json
jupyterlab_gallery-0.6.3.data/data/share/jupyter/labextensions/jupyterlab-gallery/static/728.762202b85306942083c3.js
jupyterlab_gallery-0.6.3.data/data/share/jupyter/labextensions/jupyterlab-gallery/static/906.4f604440ca2e402db4fa.js
jupyterlab_gallery-0.6.3.data/data/share/jupyter/labextensions/jupyterlab-gallery/static/936.c2a230ab873abbcc17b5.js
jupyterlab_gallery-0.6.3.data/data/share/jupyter/labextensions/jupyterlab-gallery/static/remoteEntry.2ee7e3d8eb4ee25d9ef0.js
jupyterlab_gallery-0.6.3.data/data/share/jupyter/labextensions/jupyterlab-gallery/static/style.js
jupyterlab_gallery-0.6.3.data/data/share/jupyter/labextensions/jupyterlab-gallery/static/third-party-licenses.json
jupyterlab_gallery-0.6.3.data/data/share/jupyter/labextensions/jupyterlab-gallery/install.json
jupyterlab_gallery-0.6.3.dist-info/METADATA
jupyterlab_gallery-0.6.3.dist-info/WHEEL
jupyterlab_gallery-0.6.3.dist-info/entry_points.txt
jupyterlab_gallery-0.6.3.dist-info/licenses/LICENSE
jupyterlab_gallery-0.6.3.dist-info/RECORD
