Metadata-Version: 2.3
Name: jupyterlab-gallery
Version: 0.6.3
Dynamic: Keywords
Summary: A JupyterLab gallery extension for presenting and downloading examples from remote repositories
Project-URL: Homepage, https://github.com/nebari-dev/jupyterlab-gallery
Project-URL: Bug Tracker, https://github.com/nebari-dev/jupyterlab-gallery/issues
Project-URL: Repository, https://github.com/nebari-dev/jupyterlab-gallery.git
Author-email: Nebari development team <internal-it@quansight.com>
License: BSD 3-Clause License
License-File: LICENSE
Classifier: Framework :: Jupyter
Classifier: Framework :: Jupyter :: JupyterLab
Classifier: Framework :: Jupyter :: JupyterLab :: 4
Classifier: Framework :: Jupyter :: JupyterLab :: Extensions
Classifier: Framework :: Jupyter :: JupyterLab :: Extensions :: Prebuilt
Classifier: License :: OSI Approved :: BSD License
Classifier: Programming Language :: Python
Classifier: Programming Language :: Python :: 3
Classifier: Programming Language :: Python :: 3.8
Classifier: Programming Language :: Python :: 3.9
Classifier: Programming Language :: Python :: 3.10
Classifier: Programming Language :: Python :: 3.11
Classifier: Programming Language :: Python :: 3.12
Requires-Python: >=3.8
Requires-Dist: gitpython>=3.1.43
Requires-Dist: jupyter-server<3,>=2.0.1
Requires-Dist: nbgitpuller>=1.2.1
Provides-Extra: dev
Requires-Dist: ruff==0.4.4; extra == 'dev'
Provides-Extra: test
Requires-Dist: coverage; extra == 'test'
Requires-Dist: pytest; extra == 'test'
Requires-Dist: pytest-asyncio; extra == 'test'
Requires-Dist: pytest-cov; extra == 'test'
Requires-Dist: pytest-jupyter[server]>=0.6.0; extra == 'test'
